{"nodes":[{"id":1,"name":"Visualize_Height_Field_01","meta":{"canvas_x":1.45E2,"canvas_y":-4.17E2}},{"id":5,"name":"Generate_Random_Rhs_By_Gaussian_01","meta":{"canvas_x":1.6E2,"canvas_y":-6.57E2}},{"id":11,"name":"Input_idx","meta":{"value":128,"canvas_x":-2.37E2,"canvas_y":-5.45E2}},{"id":13,"name":"Render_mesh","meta":{"canvas_x":4.22E2,"canvas_y":-5.29E2}},{"id":24,"name":"Input_bool","meta":{"value":false,"canvas_x":5.64E2,"canvas_y":-2.41E2}},{"id":26,"name":"Solve_Poission_With_Zero_Dirichlet_01_01","meta":{"canvas_x":4.77E2,"canvas_y":-6.56E2}},{"id":30,"name":"Visualize_Height_Field_01","meta":{"canvas_x":8.07E2,"canvas_y":-6.72E2}},{"id":34,"name":"Render_mesh","meta":{"canvas_x":8.22E2,"canvas_y":-4.48E2}},{"id":45,"name":"Decompose_SurfaceMesh","meta":{"canvas_x":1.7E2,"canvas_y":-2.89E2}},{"id":49,"name":"Make_SurfaceMesh","meta":{"canvas_x":2.17E2,"canvas_y":-1.61E2}},{"id":53,"name":"Elemwise_field_aft_3","meta":{"canvas_x":-2.6E1,"canvas_y":-1.92E2}},{"id":58,"name":"Input_vec3r","meta":{"x":0E0,"y":1E0,"z":0E0,"canvas_x":-2.18E2,"canvas_y":-2.07E2}},{"id":60,"name":"Make_random_vec2r","meta":{"canvas_x":-3.7E1,"canvas_y":-7.36E2}},{"id":63,"name":"Make_random_vec2r","meta":{"canvas_x":-3.7E1,"canvas_y":-6.88E2}},{"id":66,"name":"Make_random_real","meta":{"canvas_x":-3.7E1,"canvas_y":-6.4E2}},{"id":69,"name":"Write_npy_matxxr","meta":{"canvas_x":7.3E2,"canvas_y":-8.96E2}},{"id":72,"name":"Get_frame_id","meta":{"canvas_x":4.2E1,"canvas_y":-8.32E2}},{"id":74,"name":"Convert_idx_to_string","meta":{"canvas_x":1.82E2,"canvas_y":-8.32E2}},{"id":77,"name":"String_concat","meta":{"canvas_x":4.31E2,"canvas_y":-8.8E2}},{"id":81,"name":"Input_string","meta":{"value":"solution_","canvas_x":1.79E2,"canvas_y":-9.61E2}},{"id":83,"name":"Write_npy_matxxr","meta":{"canvas_x":7.3E2,"canvas_y":-8E2}},{"id":86,"name":"String_concat","meta":{"canvas_x":4.31E2,"canvas_y":-8E2}},{"id":90,"name":"Input_string","meta":{"value":"rhs_","canvas_x":1.79E2,"canvas_y":-8.97E2}},{"id":92,"name":"Input_string","meta":{"value":"Running Frame: ","canvas_x":1.79E2,"canvas_y":-1.121E3}},{"id":94,"name":"String_concat","meta":{"canvas_x":4.47E2,"canvas_y":-1.12E3}},{"id":98,"name":"Log_string_INFO","meta":{"canvas_x":6.46E2,"canvas_y":-1.12E3}},{"id":100,"name":"GlMeshCachedSequence","meta":{"canvas_x":1.018E3,"canvas_y":-5.76E2}}],"sockets":[{"id":103,"input_node":5,"input_pin":0,"output_node":1,"output_pin":0},{"id":104,"input_node":11,"input_pin":0,"output_node":5,"output_pin":0},{"id":105,"input_node":49,"input_pin":0,"output_node":13,"output_pin":1},{"id":106,"input_node":1,"input_pin":1,"output_node":13,"output_pin":2},{"id":107,"input_node":24,"input_pin":0,"output_node":13,"output_pin":6},{"id":108,"input_node":74,"input_pin":0,"output_node":94,"output_pin":1},{"id":109,"input_node":5,"input_pin":0,"output_node":26,"output_pin":0},{"id":110,"input_node":11,"input_pin":0,"output_node":26,"output_pin":1},{"id":111,"input_node":26,"input_pin":0,"output_node":30,"output_pin":0},{"id":112,"input_node":30,"input_pin":0,"output_node":34,"output_pin":1},{"id":113,"input_node":24,"input_pin":0,"output_node":34,"output_pin":6},{"id":114,"input_node":30,"input_pin":1,"output_node":34,"output_pin":2},{"id":115,"input_node":1,"input_pin":0,"output_node":45,"output_pin":0},{"id":116,"input_node":45,"input_pin":0,"output_node":53,"output_pin":0},{"id":117,"input_node":53,"input_pin":0,"output_node":49,"output_pin":0},{"id":118,"input_node":58,"input_pin":0,"output_node":53,"output_pin":2},{"id":119,"input_node":45,"input_pin":1,"output_node":49,"output_pin":1},{"id":120,"input_node":60,"input_pin":0,"output_node":5,"output_pin":1},{"id":121,"input_node":63,"input_pin":0,"output_node":5,"output_pin":2},{"id":122,"input_node":66,"input_pin":0,"output_node":5,"output_pin":3},{"id":123,"input_node":26,"input_pin":0,"output_node":69,"output_pin":0},{"id":124,"input_node":72,"input_pin":0,"output_node":74,"output_pin":0},{"id":125,"input_node":74,"input_pin":0,"output_node":77,"output_pin":1},{"id":126,"input_node":81,"input_pin":0,"output_node":77,"output_pin":0},{"id":127,"input_node":77,"input_pin":0,"output_node":69,"output_pin":1},{"id":128,"input_node":5,"input_pin":0,"output_node":83,"output_pin":0},{"id":129,"input_node":90,"input_pin":0,"output_node":86,"output_pin":0},{"id":130,"input_node":74,"input_pin":0,"output_node":86,"output_pin":1},{"id":131,"input_node":86,"input_pin":0,"output_node":83,"output_pin":1},{"id":132,"input_node":92,"input_pin":0,"output_node":94,"output_pin":0},{"id":133,"input_node":94,"input_pin":0,"output_node":98,"output_pin":0},{"id":134,"input_node":24,"input_pin":0,"output_node":34,"output_pin":7},{"id":135,"input_node":34,"input_pin":1,"output_node":100,"output_pin":0}]}